pbalancing/SBtab.py
pbalancing/SBtab_new.py
pbalancing/SBtab_old.py
pbalancing/__init__.py
pbalancing/balancer.py
pbalancing/bounded.py
pbalancing/kineticizer.py
pbalancing/misc.py
pbalancing/parameter_balancing.py
pbalancing/sbml2sbtab.py
pbalancing/sbmlmisc.py
pbalancing/sbtab2sbml.py
pbalancing/tablibIO.py
pbalancing/validatorSBtab.py
pbalancing/files/default_files/definitions.tsv
pbalancing/files/default_files/pb_options.tsv
pbalancing/files/default_files/pb_prior.tsv
pbalancing/files/example_files/ecoli/ecoli_carlsson_modified_data.tsv
pbalancing/files/example_files/ecoli/ecoli_carlsson_modified_model.xml
pbalancing/files/example_files/ecoli/ecoli_carlsson_modified_prior.tsv
pbalancing/files/example_files/hynne/BIOMD0000000061_modeldata.tsv
pbalancing/files/example_files/hynne/hynne.xml
pbalancing/files/example_files/hynne/hynne_SBtab_minmax.csv
pbalancing/files/example_files/hynne/hynne_data.tsv
pbalancing/files/example_files/hynne/hynne_inh.xml
pbalancing/files/example_files/hynne/hynne_result.tsv
pbalancing/files/example_files/jiang/jiang.xml
pbalancing/files/example_files/jiang/jiang_data.tsv
pbalancing/files/example_files/jiang/jiang_modeldata.tsv
pbalancing/files/example_files/pfk/pfk.xml
pbalancing/files/example_files/pfk/pfk_data.tsv
pbalancing/files/example_files/pfk/pfk_modeldata.tsv
pbalancing/files/example_files/pfk/pfk_result.tsv
pbalancing/files/example_files/teusink/teusink.xml
pbalancing/files/example_files/teusink/teusink_data.tsv
pbalancing/files/example_files/teusink/teusink_modeldata.tsv
pbalancing/files/example_files/teusink/teusink_result.tsv
pbalancing/files/other/kegg_reactions_CC_ph7.0.tsv
pbalancing/files/other/manual.pdf
pbalancing-2.0.16.dist-info/DESCRIPTION.rst
pbalancing-2.0.16.dist-info/METADATA
pbalancing-2.0.16.dist-info/RECORD
pbalancing-2.0.16.dist-info/WHEEL
pbalancing-2.0.16.dist-info/metadata.json
pbalancing-2.0.16.dist-info/top_level.txt
