Metadata-Version: 2.0
Name: pbalancing
Version: 2.0.16
Summary: Parameter Balancing for Kinetic Metabolic Models
Home-page: https://www.parameterbalancing.net
Author: Timo Lubitz
Author-email: timo.lubitz@gmail.com
License: MIT
Keywords: modelling systems biology kinetic parameter estimation thermodynamics
Platform: UNKNOWN
Classifier: Development Status :: 4 - Beta
Classifier: Intended Audience :: Developers
Classifier: Topic :: Software Development
Classifier: Programming Language :: Python :: 3.0
Requires-Dist: python-libsbml
Requires-Dist: tablib
